core/__init__.py
core/runner.py
core/code_scanner/__init__.py
core/code_scanner/code_scanner.py
core/providers/__init__.py
core/providers/base_ai_provider.py
core/providers/custom_ai_provider.py
core/providers/google_gemini_ai_provider.py
core/providers/open_ai_provider.py
core/utils/__init__.py
core/utils/argument_parser.py
core/utils/code_summary_extractor.py
core/utils/file_extractor.py
core/utils/provider_creator.py
codescanai-0.1.1.dist-info/LICENSE
codescanai-0.1.1.dist-info/METADATA
codescanai-0.1.1.dist-info/WHEEL
codescanai-0.1.1.dist-info/entry_points.txt
codescanai-0.1.1.dist-info/top_level.txt
codescanai-0.1.1.dist-info/RECORD
