Metadata-Version: 2.1
Name: codescanai
Version: 0.1.1
Summary: A CLI tool that scans your codebases for security vulnerabilities powered by powerful AI models.
Author-email: Caleb Abhulimhen <calebabhulimhen@gmail.com>
License: MIT
Project-URL: Homepage, https://github.com/codescan-ai/codescan
Keywords: code scanning,cli,github action,security,vulnerabilities check
Classifier: Programming Language :: Python :: 3
Classifier: License :: OSI Approved :: MIT License
Classifier: Operating System :: OS Independent
Requires-Python: >=3.10
License-File: LICENSE
Requires-Dist: openai>=1.40.6
Requires-Dist: PyGithub
Requires-Dist: requests
Requires-Dist: google-generativeai
Requires-Dist: ipython
Provides-Extra: dev
Requires-Dist: pylint; extra == "dev"
Requires-Dist: black; extra == "dev"
Requires-Dist: isort; extra == "dev"
